toffee.py
toffee-1.0.1.dist-info/LICENSE.txt
toffee-1.0.1.dist-info/METADATA
toffee-1.0.1.dist-info/WHEEL
toffee-1.0.1.dist-info/top_level.txt
toffee-1.0.1.dist-info/RECORD
