Metadata-Version: 2.1
Name: toffee
Version: 1.0.1
Summary: Toffee: Test Object Fixture Factories - easy creation of data fixtures for tests
Home-page: https://ollycope.com/software/toffee/
Author: Oliver Cope
Author-email: oliver@redgecko.org
License: Apache
Keywords: fixtures fixture factory factory_boy test testing sqlalchemy storm django
Platform: UNKNOWN
Classifier: License :: OSI Approved :: Apache Software License
Classifier: Topic :: Software Development :: Testing
Classifier: Programming Language :: Python :: 3
Classifier: Programming Language :: Python :: 3.6
Classifier: Programming Language :: Python :: 3.7
Classifier: Programming Language :: Python :: 3 :: Only
License-File: LICENSE.txt
